pyroothair/cnn.py
pyroothair/demo.py
pyroothair/images.py
pyroothair/main.py
pyroothair/mask_converter.py
pyroothair/params.py
pyroothair/pipeline.py
pyroothair/root.py
pyroothair/run_random_forest.py
pyroothair/run_single_mask.py
pyroothair/skeleton.py
pyroothair/train_random_forest.py
pyroothair/demo_images/gladiator_0001.png
pyroothair/demo_images/gladiator_0002.png
pyroothair/demo_images/gladiator_0004.png
pyroothair/demo_images/gladiator_0008.png
pyroothair/demo_images/gladiator_0015.png
pyroothair-0.0.9.dist-info/licenses/LICENSE
pyroothair-0.0.9.dist-info/METADATA
pyroothair-0.0.9.dist-info/WHEEL
pyroothair-0.0.9.dist-info/entry_points.txt
pyroothair-0.0.9.dist-info/top_level.txt
pyroothair-0.0.9.dist-info/RECORD
