Metadata-Version: 2.4
Name: pyRootHair
Version: 0.0.9
Summary: pyRootHair, a python package for automated extraction of plant root hair traits from images.
Author-email: Ian Tsang <ian.tsang@niab.com>
Maintainer-email: Ian Tsang <ian.tsang@niab.com>
License-Expression: MIT
Project-URL: Homepage, https://github.com/iantsang779/pyRootHair
Project-URL: Issues, https://github.com/iantsang779/pyRootHair/issues
Classifier: Programming Language :: Python :: 3
Classifier: Operating System :: OS Independent
Requires-Python: >=3.12
License-File: LICENSE
Requires-Dist: numpy>=2.1.0
Requires-Dist: pandas>=2.2.3
Requires-Dist: matplotlib>=3.9.0
Requires-Dist: imageio>=2.36.1
Requires-Dist: scikit-image>=0.24.0
Requires-Dist: scipy>=1.14.1
Requires-Dist: statsmodels>=0.14.4
Requires-Dist: scikit-learn>=1.5.2
Requires-Dist: nnUnetv2>=2.5.1
Requires-Dist: torch>=2.5.1
Dynamic: license-file
